django_uptime/__init__.py
django_uptime/urls.py
django_uptime/views.py
django_uptime/templates/django_uptime/index.html
django_uptime-0.5.dist-info/LICENSE
django_uptime-0.5.dist-info/METADATA
django_uptime-0.5.dist-info/WHEEL
django_uptime-0.5.dist-info/top_level.txt
django_uptime-0.5.dist-info/RECORD
