Metadata-Version: 2.1
Name: django-uptime
Version: 0.5
Summary: Editable non-cached monitorization path for Django
Home-page: https://github.com/codesyntax/django-uptime
Author: Urtzi
Author-email: uodriozola@codesyntax.eus
License: MIT license
Keywords: moritorization,uptime
Classifier: Programming Language :: Python :: 3
Classifier: Framework :: Django :: 1.11
Classifier: Framework :: Django :: 2.0
Classifier: Framework :: Django :: 3.0
Classifier: Framework :: Django :: 4.0
License-File: LICENSE
Requires-Dist: Django (>=1.11)
